{
  "annotations": {
    "list": [
      {
        "builtIn": 1,
        "datasource": "-- Grafana --",
        "enable": true,
        "hide": true,
        "iconColor": "rgba(0, 211, 255, 1)",
        "name": "Annotations & Alerts",
        "target": {
          "limit": 100,
          "matchAny": false,
          "tags": [],
          "type": "dashboard"
        },
        "type": "dashboard"
      }
    ]
  },
  "description": "NATS Server Dashboard",
  "editable": false,
  "fiscalYearStartMonth": 0,
  "graphTooltip": 0,
  "id": 28,
  "links": [],
  "liveNow": false,
  "panels": [
    {
      "collapsed": false,
      "gridPos": {
        "h": 1,
        "w": 24,
        "x": 0,
        "y": 0
      },
      "id": 14,
      "panels": [],
      "title": "Info",
      "type": "row"
    },
    {
      "fieldConfig": {
        "defaults": {
          "color": {
            "mode": "thresholds"
          },
          "custom": {
            "align": "auto",
            "displayMode": "auto"
          },
          "mappings": [],
          "thresholds": {
            "mode": "absolute",
            "steps": [
              {
                "color": "green",
                "value": null
              },
              {
                "color": "red",
                "value": 80
              }
            ]
          }
        },
        "overrides": [
          {
            "matcher": {
              "id": "byName",
              "options": "pod"
            },
            "properties": [
              {
                "id": "custom.width",
                "value": 116
              }
            ]
          },
          {
            "matcher": {
              "id": "byName",
              "options": "instance"
            },
            "properties": [
              {
                "id": "custom.width",
                "value": 288
              }
            ]
          },
          {
            "matcher": {
              "id": "byName",
              "options": "server_id"
            },
            "properties": [
              {
                "id": "custom.width",
                "value": 708
              }
            ]
          },
          {
            "matcher": {
              "id": "byName",
              "options": "Namespace"
            },
            "properties": [
              {
                "id": "custom.width",
                "value": 205
              }
            ]
          },
          {
            "matcher": {
              "id": "byName",
              "options": "Pod"
            },
            "properties": [
              {
                "id": "custom.width",
                "value": 215
              }
            ]
          }
        ]
      },
      "gridPos": {
        "h": 5,
        "w": 24,
        "x": 0,
        "y": 1
      },
      "id": 16,
      "options": {
        "footer": {
          "fields": "",
          "reducer": [
            "sum"
          ],
          "show": false
        },
        "showHeader": true,
        "sortBy": []
      },
      "pluginVersion": "8.3.3",
      "targets": [
        {
          "datasource": {
            "type": "prometheus",
            "uid": "PBFA97CFB590B2093"
          },
          "exemplar": false,
          "expr": "nats_varz_version",
          "format": "table",
          "instant": true,
          "interval": "",
          "intervalFactor": 2,
          "legendFormat": "",
          "refId": "A"
        }
      ],
      "title": "NATS pods",
      "transformations": [
        {
          "id": "filterFieldsByName",
          "options": {
            "include": {
              "names": [
                "instance",
                "pod",
                "server_id",
                "value",
                "namespace"
              ]
            }
          }
        },
        {
          "id": "organize",
          "options": {
            "excludeByName": {},
            "indexByName": {
              "instance": 3,
              "namespace": 0,
              "pod": 1,
              "server_id": 2,
              "value": 4
            },
            "renameByName": {
              "instance": "Instance",
              "namespace": "Namespace",
              "pod": "Pod",
              "server_id": "Server ID",
              "value": "Version"
            }
          }
        }
      ],
      "type": "table"
    },
    {
      "collapsed": false,
      "gridPos": {
        "h": 1,
        "w": 24,
        "x": 0,
        "y": 6
      },
      "id": 10,
      "panels": [],
      "title": "OS Metrics",
      "type": "row"
    },
    {
      "fieldConfig": {
        "defaults": {
          "color": {
            "mode": "palette-classic"
          },
          "custom": {
            "axisLabel": "",
            "axisPlacement": "auto",
            "barAlignment": 0,
            "drawStyle": "line",
            "fillOpacity": 10,
            "gradientMode": "none",
            "hideFrom": {
              "legend": false,
              "tooltip": false,
              "viz": false
            },
            "lineInterpolation": "linear",
            "lineWidth": 2,
            "pointSize": 5,
            "scaleDistribution": {
              "type": "linear"
            },
            "showPoints": "never",
            "spanNulls": false,
            "stacking": {
              "group": "A",
              "mode": "none"
            },
            "thresholdsStyle": {
              "mode": "off"
            }
          },
          "mappings": [],
          "thresholds": {
            "mode": "absolute",
            "steps": [
              {
                "color": "green",
                "value": null
              },
              {
                "color": "red",
                "value": 80
              }
            ]
          },
          "unit": "percent"
        },
        "overrides": []
      },
      "gridPos": {
        "h": 9,
        "w": 12,
        "x": 0,
        "y": 7
      },
      "id": 1,
      "links": [],
      "options": {
        "legend": {
          "calcs": [
            "mean",
            "lastNotNull",
            "max"
          ],
          "displayMode": "table",
          "placement": "bottom"
        },
        "tooltip": {
          "mode": "single"
        }
      },
      "pluginVersion": "8.3.4",
      "targets": [
        {
          "datasource": {
            "type": "prometheus",
            "uid": "PBFA97CFB590B2093"
          },
          "exemplar": true,
          "expr": "nats_varz_cpu",
          "interval": "",
          "intervalFactor": 2,
          "legendFormat": "{{pod}}",
          "metric": "gnatsd_varz_cpu",
          "refId": "A",
          "step": 4
        }
      ],
      "title": "Server CPU",
      "type": "timeseries"
    },
    {
      "fieldConfig": {
        "defaults": {
          "color": {
            "mode": "palette-classic"
          },
          "custom": {
            "axisLabel": "",
            "axisPlacement": "auto",
            "barAlignment": 0,
            "drawStyle": "line",
            "fillOpacity": 10,
            "gradientMode": "none",
            "hideFrom": {
              "legend": false,
              "tooltip": false,
              "viz": false
            },
            "lineInterpolation": "linear",
            "lineWidth": 2,
            "pointSize": 5,
            "scaleDistribution": {
              "type": "linear"
            },
            "showPoints": "never",
            "spanNulls": false,
            "stacking": {
              "group": "A",
              "mode": "none"
            },
            "thresholdsStyle": {
              "mode": "off"
            }
          },
          "mappings": [],
          "thresholds": {
            "mode": "absolute",
            "steps": [
              {
                "color": "green",
                "value": null
              },
              {
                "color": "red",
                "value": 80
              }
            ]
          },
          "unit": "bytes"
        },
        "overrides": []
      },
      "gridPos": {
        "h": 9,
        "w": 12,
        "x": 12,
        "y": 7
      },
      "id": 3,
      "links": [],
      "options": {
        "legend": {
          "calcs": [
            "mean",
            "lastNotNull",
            "max"
          ],
          "displayMode": "table",
          "placement": "bottom"
        },
        "tooltip": {
          "mode": "single"
        }
      },
      "pluginVersion": "8.3.4",
      "targets": [
        {
          "datasource": {
            "type": "prometheus",
            "uid": "PBFA97CFB590B2093"
          },
          "exemplar": true,
          "expr": "nats_varz_mem",
          "interval": "",
          "intervalFactor": 2,
          "legendFormat": "{{pod}}",
          "metric": "gnatsd_varz_mem",
          "refId": "A",
          "step": 4
        }
      ],
      "title": "Server Memory",
      "type": "timeseries"
    },
    {
      "collapsed": false,
      "gridPos": {
        "h": 1,
        "w": 24,
        "x": 0,
        "y": 16
      },
      "id": 11,
      "panels": [],
      "title": "Throughput",
      "type": "row"
    },
    {
      "fieldConfig": {
        "defaults": {
          "color": {
            "mode": "palette-classic"
          },
          "custom": {
            "axisLabel": "B/s",
            "axisPlacement": "auto",
            "barAlignment": 0,
            "drawStyle": "line",
            "fillOpacity": 10,
            "gradientMode": "none",
            "hideFrom": {
              "legend": false,
              "tooltip": false,
              "viz": false
            },
            "lineInterpolation": "linear",
            "lineWidth": 2,
            "pointSize": 5,
            "scaleDistribution": {
              "type": "linear"
            },
            "showPoints": "never",
            "spanNulls": false,
            "stacking": {
              "group": "A",
              "mode": "none"
            },
            "thresholdsStyle": {
              "mode": "off"
            }
          },
          "mappings": [],
          "thresholds": {
            "mode": "absolute",
            "steps": [
              {
                "color": "green",
                "value": null
              },
              {
                "color": "red",
                "value": 80
              }
            ]
          },
          "unit": "bytes"
        },
        "overrides": []
      },
      "gridPos": {
        "h": 9,
        "w": 6,
        "x": 0,
        "y": 17
      },
      "id": 7,
      "links": [],
      "options": {
        "legend": {
          "calcs": [
            "mean",
            "lastNotNull",
            "max"
          ],
          "displayMode": "table",
          "placement": "bottom"
        },
        "tooltip": {
          "mode": "single"
        }
      },
      "pluginVersion": "8.3.4",
      "targets": [
        {
          "datasource": {
            "type": "prometheus",
            "uid": "PBFA97CFB590B2093"
          },
          "exemplar": true,
          "expr": "rate(nats_varz_in_bytes[5m])",
          "interval": "",
          "intervalFactor": 2,
          "legendFormat": "{{pod}}",
          "metric": "gnatsd_varz_in_bytes",
          "refId": "A",
          "step": 10
        }
      ],
      "title": "Bytes per second  In",
      "type": "timeseries"
    },
    {
      "fieldConfig": {
        "defaults": {
          "color": {
            "mode": "palette-classic"
          },
          "custom": {
            "axisLabel": "msgs/s",
            "axisPlacement": "auto",
            "barAlignment": 0,
            "drawStyle": "line",
            "fillOpacity": 10,
            "gradientMode": "none",
            "hideFrom": {
              "legend": false,
              "tooltip": false,
              "viz": false
            },
            "lineInterpolation": "linear",
            "lineWidth": 2,
            "pointSize": 5,
            "scaleDistribution": {
              "type": "linear"
            },
            "showPoints": "never",
            "spanNulls": false,
            "stacking": {
              "group": "A",
              "mode": "none"
            },
            "thresholdsStyle": {
              "mode": "off"
            }
          },
          "mappings": [],
          "thresholds": {
            "mode": "absolute",
            "steps": [
              {
                "color": "green",
                "value": null
              },
              {
                "color": "red",
                "value": 80
              }
            ]
          },
          "unit": "short"
        },
        "overrides": []
      },
      "gridPos": {
        "h": 9,
        "w": 6,
        "x": 6,
        "y": 17
      },
      "id": 8,
      "links": [],
      "options": {
        "legend": {
          "calcs": [
            "mean",
            "lastNotNull",
            "max"
          ],
          "displayMode": "table",
          "placement": "bottom"
        },
        "tooltip": {
          "mode": "single"
        }
      },
      "pluginVersion": "8.3.4",
      "targets": [
        {
          "datasource": {
            "type": "prometheus",
            "uid": "PBFA97CFB590B2093"
          },
          "exemplar": true,
          "expr": "rate(nats_varz_in_msgs[5m])",
          "interval": "",
          "intervalFactor": 2,
          "legendFormat": "{{pod}}",
          "metric": "gnatsd_varz_in_msgs",
          "refId": "A",
          "step": 10
        }
      ],
      "title": "NATS Msgs per second In",
      "type": "timeseries"
    },
    {
      "fieldConfig": {
        "defaults": {
          "color": {
            "mode": "palette-classic"
          },
          "custom": {
            "axisLabel": "B/s",
            "axisPlacement": "auto",
            "barAlignment": 0,
            "drawStyle": "line",
            "fillOpacity": 10,
            "gradientMode": "none",
            "hideFrom": {
              "legend": false,
              "tooltip": false,
              "viz": false
            },
            "lineInterpolation": "linear",
            "lineWidth": 2,
            "pointSize": 5,
            "scaleDistribution": {
              "type": "linear"
            },
            "showPoints": "never",
            "spanNulls": false,
            "stacking": {
              "group": "A",
              "mode": "none"
            },
            "thresholdsStyle": {
              "mode": "off"
            }
          },
          "mappings": [],
          "thresholds": {
            "mode": "absolute",
            "steps": [
              {
                "color": "green",
                "value": null
              },
              {
                "color": "red",
                "value": 80
              }
            ]
          },
          "unit": "bytes"
        },
        "overrides": []
      },
      "gridPos": {
        "h": 9,
        "w": 6,
        "x": 12,
        "y": 17
      },
      "id": 5,
      "links": [],
      "options": {
        "legend": {
          "calcs": [
            "mean",
            "lastNotNull",
            "max"
          ],
          "displayMode": "table",
          "placement": "bottom"
        },
        "tooltip": {
          "mode": "single"
        }
      },
      "pluginVersion": "8.3.4",
      "targets": [
        {
          "datasource": {
            "type": "prometheus",
            "uid": "PBFA97CFB590B2093"
          },
          "exemplar": true,
          "expr": "rate(nats_varz_out_bytes[5m])",
          "interval": "",
          "intervalFactor": 2,
          "legendFormat": "{{pod}}",
          "metric": "gnatsd_varz_out_bytes",
          "refId": "A",
          "step": 10
        }
      ],
      "title": "Bytes per second Out",
      "type": "timeseries"
    },
    {
      "fieldConfig": {
        "defaults": {
          "color": {
            "mode": "palette-classic"
          },
          "custom": {
            "axisLabel": "msgs/s",
            "axisPlacement": "auto",
            "barAlignment": 0,
            "drawStyle": "line",
            "fillOpacity": 10,
            "gradientMode": "none",
            "hideFrom": {
              "legend": false,
              "tooltip": false,
              "viz": false
            },
            "lineInterpolation": "linear",
            "lineWidth": 2,
            "pointSize": 5,
            "scaleDistribution": {
              "type": "linear"
            },
            "showPoints": "never",
            "spanNulls": false,
            "stacking": {
              "group": "A",
              "mode": "none"
            },
            "thresholdsStyle": {
              "mode": "off"
            }
          },
          "mappings": [],
          "thresholds": {
            "mode": "absolute",
            "steps": [
              {
                "color": "green",
                "value": null
              },
              {
                "color": "red",
                "value": 80
              }
            ]
          },
          "unit": "short"
        },
        "overrides": []
      },
      "gridPos": {
        "h": 9,
        "w": 6,
        "x": 18,
        "y": 17
      },
      "id": 6,
      "links": [],
      "options": {
        "legend": {
          "calcs": [
            "mean",
            "lastNotNull",
            "max"
          ],
          "displayMode": "table",
          "placement": "bottom"
        },
        "tooltip": {
          "mode": "single"
        }
      },
      "pluginVersion": "8.3.4",
      "targets": [
        {
          "datasource": {
            "type": "prometheus",
            "uid": "PBFA97CFB590B2093"
          },
          "exemplar": true,
          "expr": "rate(nats_varz_out_msgs[5m])",
          "interval": "",
          "intervalFactor": 2,
          "legendFormat": "{{pod}}",
          "metric": "gnatsd_varz_out_msgs",
          "refId": "A",
          "step": 10
        }
      ],
      "title": "NATS Msgs per second Out",
      "type": "timeseries"
    },
    {
      "collapsed": false,
      "gridPos": {
        "h": 1,
        "w": 24,
        "x": 0,
        "y": 26
      },
      "id": 12,
      "panels": [],
      "title": "Client Metrics",
      "type": "row"
    },
    {
      "fieldConfig": {
        "defaults": {
          "color": {
            "mode": "palette-classic"
          },
          "custom": {
            "axisLabel": "",
            "axisPlacement": "auto",
            "barAlignment": 0,
            "drawStyle": "points",
            "fillOpacity": 10,
            "gradientMode": "none",
            "hideFrom": {
              "legend": false,
              "tooltip": false,
              "viz": false
            },
            "lineInterpolation": "linear",
            "lineWidth": 2,
            "pointSize": 6,
            "scaleDistribution": {
              "type": "linear"
            },
            "showPoints": "always",
            "spanNulls": false,
            "stacking": {
              "group": "A",
              "mode": "none"
            },
            "thresholdsStyle": {
              "mode": "off"
            }
          },
          "mappings": [],
          "min": 0,
          "thresholds": {
            "mode": "absolute",
            "steps": [
              {
                "color": "green",
                "value": null
              },
              {
                "color": "red",
                "value": 80
              }
            ]
          },
          "unit": "short"
        },
        "overrides": []
      },
      "gridPos": {
        "h": 9,
        "w": 8,
        "x": 0,
        "y": 27
      },
      "id": 2,
      "links": [],
      "options": {
        "legend": {
          "calcs": [
            "mean",
            "lastNotNull",
            "max"
          ],
          "displayMode": "table",
          "placement": "bottom"
        },
        "tooltip": {
          "mode": "single"
        }
      },
      "pluginVersion": "8.3.4",
      "targets": [
        {
          "datasource": {
            "type": "prometheus",
            "uid": "PBFA97CFB590B2093"
          },
          "exemplar": true,
          "expr": "nats_varz_connections",
          "interval": "",
          "intervalFactor": 1,
          "legendFormat": "{{pod}}",
          "metric": "gnatsd_varz_connections",
          "refId": "A",
          "step": 2
        }
      ],
      "title": "Connections",
      "type": "timeseries"
    },
    {
      "fieldConfig": {
        "defaults": {
          "color": {
            "mode": "palette-classic"
          },
          "custom": {
            "axisLabel": "",
            "axisPlacement": "auto",
            "barAlignment": 0,
            "drawStyle": "points",
            "fillOpacity": 10,
            "gradientMode": "none",
            "hideFrom": {
              "legend": false,
              "tooltip": false,
              "viz": false
            },
            "lineInterpolation": "linear",
            "lineWidth": 2,
            "pointSize": 6,
            "scaleDistribution": {
              "type": "linear"
            },
            "showPoints": "always",
            "spanNulls": false,
            "stacking": {
              "group": "A",
              "mode": "none"
            },
            "thresholdsStyle": {
              "mode": "off"
            }
          },
          "mappings": [],
          "min": 0,
          "thresholds": {
            "mode": "absolute",
            "steps": [
              {
                "color": "green",
                "value": null
              },
              {
                "color": "red",
                "value": 80
              }
            ]
          },
          "unit": "short"
        },
        "overrides": []
      },
      "gridPos": {
        "h": 9,
        "w": 8,
        "x": 8,
        "y": 27
      },
      "id": 4,
      "links": [],
      "options": {
        "legend": {
          "calcs": [
            "mean",
            "lastNotNull",
            "max"
          ],
          "displayMode": "table",
          "placement": "bottom"
        },
        "tooltip": {
          "mode": "single"
        }
      },
      "pluginVersion": "8.3.4",
      "targets": [
        {
          "datasource": {
            "type": "prometheus",
            "uid": "PBFA97CFB590B2093"
          },
          "exemplar": true,
          "expr": "nats_varz_subscriptions",
          "hide": false,
          "interval": "",
          "intervalFactor": 2,
          "legendFormat": "{{pod}}",
          "metric": "gnatsd_varz_subscriptions",
          "refId": "A",
          "step": 4
        }
      ],
      "title": "Subscriptions",
      "type": "timeseries"
    },
    {
      "fieldConfig": {
        "defaults": {
          "color": {
            "mode": "palette-classic"
          },
          "custom": {
            "axisLabel": "",
            "axisPlacement": "auto",
            "barAlignment": 0,
            "drawStyle": "points",
            "fillOpacity": 10,
            "gradientMode": "none",
            "hideFrom": {
              "legend": false,
              "tooltip": false,
              "viz": false
            },
            "lineInterpolation": "linear",
            "lineWidth": 2,
            "pointSize": 6,
            "scaleDistribution": {
              "type": "linear"
            },
            "showPoints": "always",
            "spanNulls": false,
            "stacking": {
              "group": "A",
              "mode": "none"
            },
            "thresholdsStyle": {
              "mode": "off"
            }
          },
          "mappings": [],
          "min": 0,
          "thresholds": {
            "mode": "absolute",
            "steps": [
              {
                "color": "green",
                "value": null
              },
              {
                "color": "red",
                "value": 80
              }
            ]
          },
          "unit": "short"
        },
        "overrides": []
      },
      "gridPos": {
        "h": 9,
        "w": 8,
        "x": 16,
        "y": 27
      },
      "id": 9,
      "links": [],
      "options": {
        "legend": {
          "calcs": [
            "mean",
            "lastNotNull",
            "max"
          ],
          "displayMode": "table",
          "placement": "bottom"
        },
        "tooltip": {
          "mode": "single"
        }
      },
      "pluginVersion": "8.3.4",
      "targets": [
        {
          "datasource": {
            "type": "prometheus",
            "uid": "PBFA97CFB590B2093"
          },
          "exemplar": true,
          "expr": "nats_varz_slow_consumers",
          "interval": "",
          "intervalFactor": 1,
          "legendFormat": "{{pod}}",
          "metric": "gnatsd_varz_slow_consumers",
          "refId": "A",
          "step": 2
        }
      ],
      "title": "Slow Consumers",
      "type": "timeseries"
    }
  ],
  "refresh": "1m",
  "schemaVersion": 34,
  "style": "dark",
  "tags": [
    "nats"
  ],
  "templating": {
    "list": []
  },
  "time": {
    "from": "now-1h",
    "to": "now"
  },
  "timepicker": {
    "refresh_intervals": [
      "5s",
      "10s",
      "30s",
      "1m",
      "5m",
      "15m",
      "30m",
      "1h",
      "2h",
      "1d"
    ],
    "time_options": [
      "5m",
      "15m",
      "1h",
      "6h",
      "12h",
      "24h",
      "2d",
      "7d",
      "30d"
    ]
  },
  "timezone": "browser",
  "title": "NATS Servers",
  "uid": "nats-servers",
  "version": 1,
  "weekStart": ""
}
